README
setup.py
text_verification_challenge/__init__.py
text_verification_challenge/test_text_verification.py
text_verification_challenge/text_verification.py
text_verification_tool.egg-info/PKG-INFO
text_verification_tool.egg-info/SOURCES.txt
text_verification_tool.egg-info/dependency_links.txt
text_verification_tool.egg-info/requires.txt
text_verification_tool.egg-info/top_level.txt
tools/text_verification.py