Metadata-Version: 1.1
Name: text-verification-tool
Version: 0.1
Summary: Compare docuemtns and find differencees.
Home-page: UNKNOWN
Author: Xingjian Pan
Author-email: xingjian.pan@thomsonreuters.com
License: UNKNOWN
Keywords: source comparision pdf xml source html
Platform: UNKNOWN
Classifier: Environment :: Console
